yatranslator/__init__.py
yatranslator/core.py
yatranslator-3.0.dist-info/METADATA
yatranslator-3.0.dist-info/WHEEL
yatranslator-3.0.dist-info/top_level.txt
yatranslator-3.0.dist-info/RECORD
