Metadata-Version: 2.1
Name: yatranslator
Version: 3.0
Summary: Async simple wrapper for Disroot Translate API
Author: sigmaboy
Requires-Python: >=3.7
Requires-Dist: aiohttp>=3.7
